exceliser/__init__.py
exceliser/__main__.py
exceliser/deserializer.py
exceliser/serializer.py
exceliser/workbook.py
exceliser-0.0.3.dist-info/LICENSE
exceliser-0.0.3.dist-info/METADATA
exceliser-0.0.3.dist-info/WHEEL
exceliser-0.0.3.dist-info/top_level.txt
exceliser-0.0.3.dist-info/RECORD
