Metadata-Version: 2.1
Name: exceliser
Version: 0.0.3
Summary: Exceliser is a tool for helping you serialize your excel documents to json or deserialize json back to excel document.
Home-page: https://github.com/pyropy/exceliser
Author: Srdjan Stankovic
Author-email: stankovic.srdjo@gmail.com
License: MIT
Download-URL: https://github.com/pyropy/exceliser/archive/0.0.2b.tar.gz
Keywords: Excel,JSON,Excel to JSON,JSON to Excel,Serializer,Deserializer
Platform: UNKNOWN
Classifier: Development Status :: 3 - Alpha
Classifier: Intended Audience :: Developers
Classifier: Topic :: Software Development :: Build Tools
Classifier: License :: OSI Approved :: MIT License
Classifier: Programming Language :: Python :: 3
Classifier: Programming Language :: Python :: 3.6
Classifier: Programming Language :: Python :: 3.7
Classifier: Programming Language :: Python :: 3.8
Requires-Dist: pytest (==5.4.1)
Requires-Dist: openpyxl (>=2.6.3)
